setup.cfg
setup.py
Flask_S3_Bower.egg-info/PKG-INFO
Flask_S3_Bower.egg-info/SOURCES.txt
Flask_S3_Bower.egg-info/dependency_links.txt
Flask_S3_Bower.egg-info/not-zip-safe
Flask_S3_Bower.egg-info/requires.txt
Flask_S3_Bower.egg-info/top_level.txt
flask_s3_bower/__init__.py
flask_s3_bower/flask_bower.py
flask_s3_bower/flask_s3.py