Metadata-Version: 1.1
Name: Flask-S3-Bower
Version: 0.6
Summary: Seamlessly serve the static files of your Flask app from Amazon S3 and also use bower for development
Home-page: https://github.com/ibrahim12/flask-s3-bower
Author: Ibrahim Rashid
Author-email: irashid.com@gmail.com
License: GNU
Download-URL: https://github.com/ibrahim12/Flask-S3-Bower/tarball/0.6
Keywords: flask_s3_bower,flask bower,flask s3,serve static file flask s3 bower
Platform: any
Classifier: Environment :: Web Environment
Classifier: Intended Audience :: Developers
Classifier: License :: Other/Proprietary License
Classifier: Operating System :: OS Independent
Classifier: Programming Language :: Python
Classifier: Topic :: Internet :: WWW/HTTP :: Dynamic Content
Classifier: Topic :: Software Development :: Libraries :: Python Modules
